{"cameraMode":{"drawMode":0,"name":"Shaded","section":"Shading Mode"},"sceneLighting":true,"audioPlay":false,"sceneViewState":{"showFog":true,"showMaterialUpdate":false,"showSkybox":true,"showFlares":true,"showImageEffects":true,"showParticleSystems":true},"in2DMode":false,"pivot":{"x":-41.385704040527347,"y":-7.5231781005859379,"z":23.025550842285158},"rotation":{"x":0.4615205228328705,"y":-0.04283331707119942,"z":0.02231668122112751,"w":0.88581383228302},"size":28.65406036376953,"orthographic":false}