{"cameraMode":{"drawMode":0,"name":"Shaded","section":"Shading Mode"},"sceneLighting":true,"audioPlay":false,"sceneViewState":{"showFog":true,"showMaterialUpdate":false,"showSkybox":true,"showFlares":true,"showImageEffects":true,"showParticleSystems":true},"in2DMode":false,"pivot":{"x":-1.399204969406128,"y":3.4166393280029299,"z":-1.1854591369628907},"rotation":{"x":-0.05934973433613777,"y":0.9261690974235535,"z":-0.16452810168266297,"w":-0.33409425616264346},"size":13.63250732421875,"orthographic":false}